qcb_plotting_tools/__init__.py
qcb_plotting_tools/qcbplotting.py
qcb_plotting_tools/version.py
qcb_plotting_tools/bin/__init__.py
qcb_plotting_tools/bin/load_and_save_data.py
qcb_plotting_tools/bin/qcb_drug_analysis_template.py
qcb_plotting_tools/test/__init__.py
qcb_plotting_tools/test/test_import.py
qcb_plotting_tools-0.0.1.dist-info/LICENSE.txt
qcb_plotting_tools-0.0.1.dist-info/METADATA
qcb_plotting_tools-0.0.1.dist-info/WHEEL
qcb_plotting_tools-0.0.1.dist-info/top_level.txt
qcb_plotting_tools-0.0.1.dist-info/RECORD
