Metadata-Version: 2.1
Name: qcb-plotting-tools
Version: 0.0.1
Summary: Plotting and Analysis tools for QCB
Home-page: UNKNOWN
Author: AICS
Author-email: your_aics_email@alleninstitute.org
License: Allen Institute Software License
Platform: UNKNOWN
Requires-Dist: seaborn
Requires-Dist: pandas
Requires-Dist: matplotlib
Requires-Dist: scikit-learn
Requires-Dist: scipy
Requires-Dist: numpy
Provides-Extra: all
Requires-Dist: pytest ; extra == 'all'
Requires-Dist: pytest-cov ; extra == 'all'
Requires-Dist: flake8 ; extra == 'all'
Provides-Extra: interactive_dev_group
Provides-Extra: lint_group
Requires-Dist: flake8 ; extra == 'lint_group'
Provides-Extra: test_group
Requires-Dist: pytest ; extra == 'test_group'
Requires-Dist: pytest-cov ; extra == 'test_group'
